AUTHORS
ChangeLog
MANIFEST.in
README.rst
setup.cfg
setup.py
leonardo_module_links/__init__.py
leonardo_module_links/admin.py
leonardo_module_links/forms.py
leonardo_module_links/models.py
leonardo_module_links/tables.py
leonardo_module_links.egg-info/PKG-INFO
leonardo_module_links.egg-info/SOURCES.txt
leonardo_module_links.egg-info/dependency_links.txt
leonardo_module_links.egg-info/not-zip-safe
leonardo_module_links.egg-info/pbr.json
leonardo_module_links.egg-info/top_level.txt
leonardo_module_links/locale/cs/LC_MESSAGES/django.po
leonardo_module_links/locale/de/LC_MESSAGES/django.po
leonardo_module_links/locale/sk/LC_MESSAGES/django.po
leonardo_module_links/migrations/0001_initial.py
leonardo_module_links/migrations/0002_auto_20160323_1607.py
leonardo_module_links/migrations/__init__.py
leonardo_module_links/static/css/bootstrap-social.css
leonardo_module_links/static/img/forkme_right_green.png
leonardo_module_links/templates/widget/linkbutton/default.html
leonardo_module_links/templates/widget/linkmenu/_faqs.html
leonardo_module_links/templates/widget/linkmenu/_icon.html
leonardo_module_links/templates/widget/linkmenu/_item.html
leonardo_module_links/templates/widget/linkmenu/_social.html
leonardo_module_links/templates/widget/linkmenu/_vertical.html
leonardo_module_links/templates/widget/linkmenu/banners.html
leonardo_module_links/templates/widget/linkmenu/default.html
leonardo_module_links/templates/widget/linkmenu/detail.html
leonardo_module_links/templates/widget/linkmenu/faqs.html
leonardo_module_links/templates/widget/linkmenu/icons.html
leonardo_module_links/templates/widget/linkmenu/social.html
leonardo_module_links/templates/widget/linkmenu/sticker.html
leonardo_module_links/widget/__init__.py
leonardo_module_links/widget/models.py
leonardo_module_links/widget/linkbutton/__init__.py
leonardo_module_links/widget/linkbutton/forms.py
leonardo_module_links/widget/linkbutton/models.py
leonardo_module_links/widget/linkmenu/__init__.py
leonardo_module_links/widget/linkmenu/forms.py
leonardo_module_links/widget/linkmenu/models.py